rpbot/__init__.py
rpbot/__main__.py
rpbot/run.py
rpbot/reader/__init__.py
rpbot/reader/reader_options.py
rpbot/reader/robot_results_parser.py
rpbot/reportportal/__init__.py
rpbot/reportportal/model.py
rpbot/reportportal/reporter.py
rpbot/reportportal/service.py
rpbot/reportportal/variables.py
utest/__init__.py
utest/test_robot_result_parser.py
rpbot-0.31.dist-info/LICENSE.txt
rpbot-0.31.dist-info/METADATA
rpbot-0.31.dist-info/WHEEL
rpbot-0.31.dist-info/top_level.txt
rpbot-0.31.dist-info/RECORD
