Metadata-Version: 2.1
Name: rpbot
Version: 0.31
Summary: A tool for inserting Robot Framework test run results into ReportPortal.
Home-page: https://github.com/doyou89/RPBot
Author: Doyou Jung
Author-email: doyou89@gmail.com
License: Apache License 2.0
Download-URL: https://pypi.python.org/pypi/rpbot
Keywords: robotframework testing testautomation atdd
Platform: any
Classifier: Development Status :: 4 - Beta
Classifier: Operating System :: OS Independent
Classifier: Programming Language :: Python
Classifier: Topic :: Software Development :: Testing
Requires-Dist: six
Requires-Dist: robotframework
Requires-Dist: reportportal-client
